{
  "date": "2026-04-29",
  "games": [
    {
      "teams": [
        "ATL",
        "NYK"
      ],
      "scores": [
        57,
        73
      ],
      "status": "live",
      "gameId": "0042500125",
      "clock": "PT07M54.00S",
      "period": 3
    },
    {
      "teams": [
        "PHI",
        "BOS"
      ],
      "scores": [
        113,
        97
      ],
      "status": "final",
      "gameId": "0042500115",
      "clock": "",
      "period": 4
    },
    {
      "teams": [
        "POR",
        "SAS"
      ],
      "scores": null,
      "status": "scheduled",
      "gameId": "0042500155",
      "clock": "",
      "period": 0
    }
  ]
}