{
  "date": "2026-05-02",
  "games": [
    {
      "teams": [
        "CLE",
        "TOR"
      ],
      "scores": [
        32,
        34
      ],
      "status": "live",
      "gameId": "0042500136",
      "clock": "PT11M34.00S",
      "period": 2
    },
    {
      "teams": [
        "DET",
        "ORL"
      ],
      "scores": [
        38,
        60
      ],
      "status": "live",
      "gameId": "0042500106",
      "clock": "PT00M00.00S",
      "period": 2
    },
    {
      "teams": [
        "LAL",
        "HOU"
      ],
      "scores": null,
      "status": "scheduled",
      "gameId": "0042500176",
      "clock": "",
      "period": 0
    }
  ]
}