{
  "date": "2026-04-25",
  "games": [
    {
      "teams": [
        "BOS",
        "PHI"
      ],
      "scores": [
        103,
        100
      ],
      "status": "live",
      "gameId": "0042500113",
      "clock": "PT00M59.50S",
      "period": 4
    },
    {
      "teams": [
        "LAL",
        "HOU"
      ],
      "scores": [
        67,
        62
      ],
      "status": "live",
      "gameId": "0042500173",
      "clock": "PT06M52.00S",
      "period": 3
    },
    {
      "teams": [
        "SAS",
        "POR"
      ],
      "scores": null,
      "status": "scheduled",
      "gameId": "0042500153",
      "clock": "",
      "period": 0
    }
  ]
}