{
  "date": "2026-04-28",
  "games": [
    {
      "teams": [
        "DET",
        "ORL"
      ],
      "scores": [
        14,
        21
      ],
      "status": "live",
      "gameId": "0042500104",
      "clock": "PT04M57.00S",
      "period": 1
    },
    {
      "teams": [
        "OKC",
        "PHO"
      ],
      "scores": null,
      "status": "scheduled",
      "gameId": "0042500144",
      "clock": "",
      "period": 0
    },
    {
      "teams": [
        "MIN",
        "DEN"
      ],
      "scores": null,
      "status": "scheduled",
      "gameId": "0042500165",
      "clock": "",
      "period": 0
    }
  ]
}